dessin_snt/__init__.py
dessin_snt/dessin_snt.py
dessin_snt-0.2.0.dist-info/METADATA
dessin_snt-0.2.0.dist-info/WHEEL
dessin_snt-0.2.0.dist-info/top_level.txt
dessin_snt-0.2.0.dist-info/RECORD
